pysbus/__init__.py
pysbus/constants.py
pysbus/sbus.py
pysbus/serial_parser.py
pysbus/softserial_parser.py
pysbus/debug/__init__.py
pysbus/debug/serial_print_bytes.py
pysbus/debug/serial_print_channels.py
pysbus/debug/serial_print_payload.py
pysbus/debug/softserial_print_bytes.py
pysbus/debug/softserial_print_channels.py
pysbus/debug/softserial_print_payload.py
tarantul_server/__init__.py
tarantul_server/drone_firmware.py
tarantul_server/gps_handler.py
tarantul_server/mavlink_connection.py
tarantul_server/network_signal_settings.py
tarantul_server/sbus_communication.py
tarantul_server-0.1.dist-info/METADATA
tarantul_server-0.1.dist-info/WHEEL
tarantul_server-0.1.dist-info/entry_points.txt
tarantul_server-0.1.dist-info/top_level.txt
tarantul_server-0.1.dist-info/RECORD
